kvadrat/__init__.py
kvadrat/__main__.py
kvadrat/bitmap.py
kvadrat/polygon.py
kvadrat/svg_.py
kvadrat/util.py
kvadrat-0.1.1.dist-info/entry_points.txt
kvadrat-0.1.1.dist-info/LICENSE
kvadrat-0.1.1.dist-info/METADATA
kvadrat-0.1.1.dist-info/WHEEL
kvadrat-0.1.1.dist-info/RECORD
