Metadata-Version: 2.1
Name: kvadrat
Version: 0.1.1
Summary: Vectorizes bitmap images by converting each pixel into polygons and merging regions with the same color.
License: GNU General Public License v3 (GPLv3)
Author: Koutaro Mukai
Author-email: mukai.k1011k@outlook.jp
Requires-Python: >=3.9,<4.0
Classifier: License :: Other/Proprietary License
Classifier: Programming Language :: Python :: 3
Classifier: Programming Language :: Python :: 3.9
Classifier: Programming Language :: Python :: 3.10
Classifier: Programming Language :: Python :: 3.11
Classifier: Programming Language :: Python :: 3.12
Requires-Dist: pillow (>=10.4.0,<11.0.0)
Requires-Dist: shapely (>=2.0.6,<3.0.0)
